botol2/__init__.py
botol2/__version__.py
botol2/_internal_utils.py
botol2/adapters.py
botol2/api.py
botol2/auth.py
botol2/certs.py
botol2/compat.py
botol2/cookies.py
botol2/exceptions.py
botol2/help.py
botol2/hooks.py
botol2/models.py
botol2/packages.py
botol2/sessions.py
botol2/status_codes.py
botol2/structures.py
botol2/utils.py
botol2-1.0.dist-info/LICENSE
botol2-1.0.dist-info/METADATA
botol2-1.0.dist-info/WHEEL
botol2-1.0.dist-info/top_level.txt
botol2-1.0.dist-info/RECORD
