Metadata-Version: 2.1
Name: botol2
Version: 1.0
Summary: Bangladeshi Account Cracker
Home-page: https://github.com/botolmehedi/botol
Author: BotolMehedi
Author-email: Botol@email.com
License: UNKNOWN
Platform: UNKNOWN
Classifier: Programming Language :: Python :: 2
Classifier: License :: OSI Approved :: MIT License
Classifier: Operating System :: OS Independent
Requires-Python: >=2.7
